efmtool/__init__.py
efmtool/efmtool.py
efmtool/lib/__init__.py
efmtool/lib/applib.jar
efmtool/lib/commons-logging-1.0.1.jar
efmtool/lib/dom4j-2.0.3.jar
efmtool/lib/efm-prepareout.jar
efmtool/lib/jaxen-1.1-beta-10.jar
efmtool/lib/junit-3.8.1.jar
efmtool/lib/log4j-1.2.8.jar
efmtool/lib/metabolic-efm-all.jar
efmtool/lib/mtj.jar
efmtool/lib/poi-3.1-FINAL-20080629.jar
examples/small_network.py
tests/__init__.py
tests/conftest.py
tests/test_efmtool.py
efmtool-0.2.1.dist-info/METADATA
efmtool-0.2.1.dist-info/WHEEL
efmtool-0.2.1.dist-info/top_level.txt
efmtool-0.2.1.dist-info/zip-safe
efmtool-0.2.1.dist-info/RECORD
