Metadata-Version: 2.1
Name: efmtool
Version: 0.2.1
Summary: Python wrapper for efmtool
Author-email: Mattia Gollub <mattia.gollub@gmail.com>
License: BSD License
Project-URL: repository, https://gitlab.com/csb.ethz/efmtool
Keywords: EFM,EFMs,Elementary Flux Modes,efmtool,metabolic network,reaction network
Classifier: Development Status :: 4 - Beta
Classifier: Intended Audience :: Science/Research
Classifier: Topic :: Scientific/Engineering :: Bio-Informatics
Classifier: License :: OSI Approved :: BSD License
Classifier: Natural Language :: English
Classifier: Programming Language :: Python :: 3
Classifier: Programming Language :: Python :: 3.8
Classifier: Programming Language :: Python :: 3.9
Classifier: Programming Language :: Python :: 3.10
Classifier: Programming Language :: Python :: 3.11
Requires-Python: >=3.6
Requires-Dist: JPype1 (>=1.1.2)
Requires-Dist: numpy (>=1.14)
Requires-Dist: scipy (>=1.4)
Provides-Extra: test
Requires-Dist: pytest ; extra == 'test'
